potatoscript/potatoConfig.py
python/potatoConfig.py
python/xConfigparser.py
xConfigparser-1.0.0.dist-info/METADATA
xConfigparser-1.0.0.dist-info/WHEEL
xConfigparser-1.0.0.dist-info/top_level.txt
xConfigparser-1.0.0.dist-info/RECORD
