Metadata-Version: 2.1
Name: xConfigparser
Version: 1.0.0
Summary: A simple library for getting the value from config.ini
Author: ks lim
Author-email: kianseng.lim@sony.com
